MontgomeryReductionAlgorithm/__init__.py
MontgomeryReductionAlgorithm/cli.py
MontgomeryReductionAlgorithm/gui.py
MontgomeryReductionAlgorithm/mmr.py
MontgomeryReductionAlgorithm/srsa.py
MontgomeryReductionAlgorithm/test.py
montgomery_reduction_algorithm-0.0.5a0.dist-info/licenses/LICENSE
montgomery_reduction_algorithm-0.0.5a0.dist-info/METADATA
montgomery_reduction_algorithm-0.0.5a0.dist-info/WHEEL
montgomery_reduction_algorithm-0.0.5a0.dist-info/entry_points.txt
montgomery_reduction_algorithm-0.0.5a0.dist-info/top_level.txt
montgomery_reduction_algorithm-0.0.5a0.dist-info/RECORD
