Metadata-Version: 2.4
Name: Montgomery-Reduction-Algorithm
Version: 0.0.5a0
Summary: Montgomery Reduction Algorithm python package to verify and study hardware implementations.
Author-email: "Andreas W. Weber" <andreas.willibald.weber@gmail.com>
Maintainer-email: "Andreas W. Weber" <andreas.willibald.weber@gmail.com>
License-Expression: MIT
Project-URL: Homepage, https://github.com/AndreasWillibaldWeber/Montgomery-Reduction-Algorithm
Project-URL: Issues, https://github.com/AndreasWillibaldWeber/Montgomery-Reduction-Algorithm/issues
Project-URL: Documentation, https://github.com/AndreasWillibaldWeber/Montgomery-Reduction-Algorithm
Project-URL: Repository, https://github.com/AndreasWillibaldWeber/Montgomery-Reduction-Algorithm
Keywords: Montgomery,reduction,algorithm,multiplication,exponentiation,hardware,study,research
Classifier: Intended Audience :: Science/Research
Classifier: Development Status :: 2 - Pre-Alpha
Classifier: Programming Language :: Python :: 3
Classifier: Operating System :: OS Independent
Requires-Python: >=3.8
License-File: LICENSE
Dynamic: license-file
